gng/__init__.py
gng/__main__.py
gng/cli/commands/root_command.py
gng/cli/helpers/__init__.py
gng/cli/helpers/converter.py
gng/cli/styling/__init__.py
gng/cli/styling/output.py
gng/cli/styling/themes.py
gng/config/__init__.py
gng/config/constants.py
gng/core/__init__.py
gng/core/mappings.py
gng/core/validator.py
gng/logging/__init__.py
gng/logging/formatters.py
gng/logging/parsers.py
gng/logging/text_tools.py
go_or_no_go-0.1.0a3.dist-info/METADATA
go_or_no_go-0.1.0a3.dist-info/WHEEL
go_or_no_go-0.1.0a3.dist-info/entry_points.txt
go_or_no_go-0.1.0a3.dist-info/licenses/LICENCE
go_or_no_go-0.1.0a3.dist-info/RECORD
