Metadata-Version: 2.4
Name: go-or-no-go
Version: 0.1.0a3
Summary: Pre-commit hooks to check that your contributions meet project guidelines and the mission to merge is good to go!
License: MIT
License-File: LICENCE
Author: Manoel Pereira de Queiroz
Author-email: mpq.dev@pm.me
Maintainer: Manoel Pereira de Queiroz
Maintainer-email: mpq.dev@pm.me
Requires-Python: >=3.10
Classifier: Development Status :: 1 - Planning
Classifier: Environment :: Console
Classifier: License :: OSI Approved :: MIT License
Classifier: Operating System :: OS Independent
Classifier: Programming Language :: Python :: 3
Classifier: Programming Language :: Python :: 3.10
Classifier: Programming Language :: Python :: 3.11
Classifier: Programming Language :: Python :: 3.12
Classifier: Programming Language :: Python :: 3.13
Classifier: Programming Language :: Python :: 3.14
Classifier: Topic :: Software Development :: Libraries :: Python Modules
Classifier: Topic :: Terminals
Requires-Dist: click (>=8.1.0,<8.2.0)
Requires-Dist: gitpython (>=3.1.45,<4.0.0)
Requires-Dist: nebulog (>=0.1.0,<0.2.0)
Requires-Dist: platformdirs (>=4.5.0,<5.0.0)
Requires-Dist: pydriller (>=2.9,<3.0)
Requires-Dist: rich (>=14.2.0,<15.0.0)
Requires-Dist: tomli (>=2.3.0,<3.0.0) ; python_version < "3.11"
Requires-Dist: typer[all] (>=0.20.0,<0.21.0)
Project-URL: Contributing Guidelines, https://gitlab.com/galactipy/utilities/go-no-go/-/tree/master/CONTRIBUTING.md
Project-URL: Homepage, https://gitlab.com/galactipy/utilities/go-no-go
Project-URL: Repository, https://gitlab.com/galactipy/utilities/go-no-go
Project-URL: Work Item Tracker, https://gitlab.com/galactipy/utilities/go-no-go/-/issues
